beetsplug/__init__.py
beetsplug/redacted/__init__.py
beetsplug/redacted/client.py
beetsplug/redacted/command.py
beetsplug/redacted/exceptions.py
beetsplug/redacted/http.py
beetsplug/redacted/matching.py
beetsplug/redacted/search.py
beetsplug/redacted/types.py
beetsplug/redacted/utils/__init__.py
beetsplug/redacted/utils/search_utils.py
beetsplug/redacted/utils/test_utils.py
beets_redacted-0.1.1.dist-info/LICENSE.txt
beets_redacted-0.1.1.dist-info/METADATA
beets_redacted-0.1.1.dist-info/WHEEL
beets_redacted-0.1.1.dist-info/RECORD
