Metadata-Version: 2.3
Name: beets-redacted
Version: 0.1.1
Summary: A Redacted plugin for Beets.
License: MIT
Author: Judas Iscariot
Author-email: judas@noreply.com
Requires-Python: >=3.9,<4
Classifier: License :: OSI Approved :: MIT License
Classifier: Programming Language :: Python :: 3
Classifier: Programming Language :: Python :: 3.9
Classifier: Programming Language :: Python :: 3.10
Classifier: Programming Language :: Python :: 3.11
Classifier: Programming Language :: Python :: 3.12
Classifier: Programming Language :: Python :: 3.13
Requires-Dist: backoff (>=2.2.1,<3.0.0)
Requires-Dist: beets (>=1.6.0)
Requires-Dist: diskcache (>=5.6.3,<6.0.0)
Requires-Dist: enlighten (>=1.12.0,<2.0.0)
Requires-Dist: frozendict (>=2.4.6,<3.0.0)
Requires-Dist: pydantic (>=2.11.1,<3.0.0)
Requires-Dist: ratelimit (>=2.2.1,<3.0.0)
Requires-Dist: requests (>=2.31.0)
Project-URL: Homepage, https://github.com/judas-red/beets-redacted
Project-URL: Repository, https://github.com/judas-red/beets-redacted.git
